openweather/__init__.py
openweather/weather.py
tests/functional_testing.py
tests/test.py
tests/test_api_wrapper.py
openweather_wrapper-0.1.1.dist-info/LICENSE
openweather_wrapper-0.1.1.dist-info/METADATA
openweather_wrapper-0.1.1.dist-info/WHEEL
openweather_wrapper-0.1.1.dist-info/top_level.txt
openweather_wrapper-0.1.1.dist-info/RECORD
