Metadata-Version: 2.1
Name: openweather-wrapper
Version: 0.1.1
Summary: A Python wrapper for the OpenWeatherMap API to fetch weather data.
Home-page: https://github.com/SHRISH01/openweather-wrapper
Author: Shrish Kamboj
Author-email: Shrish Kamboj <shrishkamboj@gmail.com>
License: MIT License
Project-URL: Homepage, https://github.com/SHRISH01/openweather-wrapper
Project-URL: Bug-Tracker, https://github.com/SHRISH01/openweather-wrapper/issues
Keywords: weather,openweathermap,api,wrapper,python
Classifier: Programming Language :: Python :: 3
Classifier: License :: OSI Approved :: MIT License
Classifier: Operating System :: OS Independent
Requires-Python: >=3.12.0
License-File: LICENSE
Requires-Dist: requests>=2.31.0
